itk/PolarTransformPython.py
itk/_PolarTransformPython.pyd
itk/itkCartesianToPolarTransformPython.py
itk/itkPolarToCartesianTransformPython.py
itk/Configuration/PolarTransformConfig.py
itk_polartransform-1.1.2.dist-info/LICENSE
itk_polartransform-1.1.2.dist-info/METADATA
itk_polartransform-1.1.2.dist-info/WHEEL
itk_polartransform-1.1.2.dist-info/top_level.txt
itk_polartransform-1.1.2.dist-info/RECORD
