Metadata-Version: 2.1
Name: itk-polartransform
Version: 1.1.2
Summary: This module contains ITK classes to transform from cartesian to polar coordinate systems and back.
Home-page: https://itk.org/
Author: Insight Software Consortium
Author-email: itk+community@discourse.itk.org
License: Apache
Download-URL: https://github.com/InsightSoftwareConsortium/ITKPolarTransform
Keywords: ITK InsightToolkit
Platform: UNKNOWN
Classifier: License :: OSI Approved :: Apache Software License
Classifier: Programming Language :: Python
Classifier: Programming Language :: C++
Classifier: Development Status :: 4 - Beta
Classifier: Intended Audience :: Developers
Classifier: Intended Audience :: Education
Classifier: Intended Audience :: Healthcare Industry
Classifier: Intended Audience :: Science/Research
Classifier: Topic :: Scientific/Engineering
Classifier: Topic :: Scientific/Engineering :: Medical Science Apps.
Classifier: Topic :: Scientific/Engineering :: Information Analysis
Classifier: Topic :: Software Development :: Libraries
Classifier: Operating System :: Android
Classifier: Operating System :: Microsoft :: Windows
Classifier: Operating System :: POSIX
Classifier: Operating System :: Unix
Classifier: Operating System :: MacOS
Requires-Dist: itk-core (>=5.1.1.post1)
